odoo/addons/fieldservice_operating_unit/README.rst
odoo/addons/fieldservice_operating_unit/__init__.py
odoo/addons/fieldservice_operating_unit/__manifest__.py
odoo/addons/fieldservice_operating_unit/i18n/fieldservice_operating_unit.pot
odoo/addons/fieldservice_operating_unit/i18n/pt.po
odoo/addons/fieldservice_operating_unit/models/__init__.py
odoo/addons/fieldservice_operating_unit/models/fsm_order.py
odoo/addons/fieldservice_operating_unit/readme/CONTRIBUTORS.rst
odoo/addons/fieldservice_operating_unit/readme/CREDITS.rst
odoo/addons/fieldservice_operating_unit/readme/DESCRIPTION.rst
odoo/addons/fieldservice_operating_unit/readme/USAGE.rst
odoo/addons/fieldservice_operating_unit/security/fieldservice_security.xml
odoo/addons/fieldservice_operating_unit/static/description/icon.png
odoo/addons/fieldservice_operating_unit/static/description/index.html
odoo/addons/fieldservice_operating_unit/tests/__init__.py
odoo/addons/fieldservice_operating_unit/tests/test_fieldservice_operating_unit.py
odoo/addons/fieldservice_operating_unit/views/fsm_order.xml
odoo12_addon_fieldservice_operating_unit-12.0.1.0.0.99.dev6.dist-info/METADATA
odoo12_addon_fieldservice_operating_unit-12.0.1.0.0.99.dev6.dist-info/WHEEL
odoo12_addon_fieldservice_operating_unit-12.0.1.0.0.99.dev6.dist-info/top_level.txt
odoo12_addon_fieldservice_operating_unit-12.0.1.0.0.99.dev6.dist-info/RECORD
