Metadata-Version: 2.1
Name: odoo12-addon-fieldservice-operating-unit
Version: 12.0.1.0.0.99.dev6
Summary: This module adds operating unit information to Field Service orders.
Home-page: https://github.com/OCA/operating-unit
Author: Open Source Integrators, Serpent Consulting Services Pvt. Ltd.,Odoo Community Association (OCA)
Author-email: support@odoo-community.org
License: AGPL-3
Platform: UNKNOWN
Classifier: Programming Language :: Python
Classifier: Framework :: Odoo
Classifier: Framework :: Odoo :: 12.0
Classifier: License :: OSI Approved :: GNU Affero General Public License v3
Classifier: Development Status :: 4 - Beta
Requires-Python: >=3.5
Requires-Dist: odoo12-addon-fieldservice
Requires-Dist: odoo12-addon-operating-unit
Requires-Dist: odoo <12.1dev,>=12.0a
